setup.py
rocketeer/__init__.py
rocketeer/app.py
rocketeer/client.py
rocketeer/daemon.py
rocketeer/process.py
rocketeer/server.py
rocketeer/staticprocess.py
rocketeer/synch.py
rocketeer.egg-info/PKG-INFO
rocketeer.egg-info/SOURCES.txt
rocketeer.egg-info/dependency_links.txt
rocketeer.egg-info/requires.txt
rocketeer.egg-info/top_level.txt
rocketeer/tests/__init__.py
rocketeer/tests/test.py
rocketeer/tests/testclient.py
rocketeer/tests/testserver.py
rocketeer/tests/teststream.py