Metadata-Version: 1.0
Name: rocketeer
Version: 0.2
Summary: Advanced remote process launcher, watchdog and manager.
Home-page: https://github.com/offlinehacker/rocketeer
Author: Jaka Hudoklin
Author-email: jakahudoklin@gmail.com
License: GNU
Keywords: process launcher remote ffmpeg
Platform: UNKNOWN
Classifier: Development Status :: 4 - Beta
Classifier: Topic :: Utilities
Classifier: License :: OSI Approved :: GNU General Public License (GPL)
